<?xml version="1.0" encoding="UTF-8"?>
<beans xmlns="http://www.springframework.org/schema/beans"
	xmlns:xsi="http://www.w3.org/2001/XMLSchema-instance"
	xsi:schemaLocation="http://www.springframework.org/schema/beans http://www.springframework.org/schema/beans/spring-beans-3.0.xsd">

	<!-- Root Context: defines shared resources visible to all other web components -->

	<!-- JPA stuff -->

	<bean id="dataSource"
		class="org.springframework.jdbc.datasource.DriverManagerDataSource">
		<property name="driverClassName" value="com.mysql.jdbc.Driver"></property>
		<property name="url" value="jdbc:mysql://localhost:3306/khanavali" />
		<property name="username" value="root"></property>
		<property name="password" value="khanavali123"></property>
	</bean>

	<bean id="entityManagerFactory"
		class="org.springframework.orm.jpa.LocalContainerEntityManagerFactoryBean">
		<property name="dataSource" ref="dataSource"></property>
		<property name="jpaVendorAdapter" ref="jpaVendorAdapter"></property>
		<property name="packagesToScan" value="com.khanavali.model.persistence"></property>
	</bean>

	<bean id="jpaVendorAdapter"
		class="org.springframework.orm.jpa.vendor.HibernateJpaVendorAdapter">
		<property name="showSql" value="true"></property>
		<property name="database"
			value="org.springframework.orm.jpa.vendor.Database.MYSQL"></property>
		<property name="generateDdl" value="false"></property>
	</bean>

	<bean id="transactionManager" class="org.springframework.orm.jpa.JpaTransactionManager">
	</bean>


</beans>
